nms_translator/__init__.py
nms_translator/__main__.py
nms_translator/cli.py
nms_translator/grabber.py
nms_translator/textract.py
nms_translator/translator.py
nms_ts-1.1.3.dist-info/LICENSE
nms_ts-1.1.3.dist-info/METADATA
nms_ts-1.1.3.dist-info/WHEEL
nms_ts-1.1.3.dist-info/entry_points.txt
nms_ts-1.1.3.dist-info/RECORD
