Metadata-Version: 2.1
Name: nms-ts
Version: 1.1.3
Summary: A tool for grabbing binary text from a No Man's Sky screenshot and translating it to UTF-8 for you.
Author: Dakota Brown
Author-email: dakota.kae.brown@gmail.com
Requires-Python: >=3.9,<3.13
Classifier: Programming Language :: Python :: 3
Classifier: Programming Language :: Python :: 3.9
Classifier: Programming Language :: Python :: 3.10
Classifier: Programming Language :: Python :: 3.11
Requires-Dist: click (>=8.1.7,<9.0.0)
Requires-Dist: pillow (>=10.0.0,<11.0.0)
Requires-Dist: pytesseract (>=0.3.10,<0.4.0)
Requires-Dist: toml (>=0.10.2,<0.11.0)
